normal_captcha/__init__.py
normal_captcha/main.py
normal_captcha-2023.5.15.1604.dist-info/entry_points.txt
normal_captcha-2023.5.15.1604.dist-info/WHEEL
normal_captcha-2023.5.15.1604.dist-info/METADATA
normal_captcha-2023.5.15.1604.dist-info/RECORD
